odoo/addons/stock_release_channel_propagate_channel_picking/README.rst
odoo/addons/stock_release_channel_propagate_channel_picking/__init__.py
odoo/addons/stock_release_channel_propagate_channel_picking/__manifest__.py
odoo/addons/stock_release_channel_propagate_channel_picking/i18n/it.po
odoo/addons/stock_release_channel_propagate_channel_picking/i18n/stock_release_channel_propagate_channel_picking.pot
odoo/addons/stock_release_channel_propagate_channel_picking/models/__init__.py
odoo/addons/stock_release_channel_propagate_channel_picking/models/stock_move.py
odoo/addons/stock_release_channel_propagate_channel_picking/models/stock_picking_type.py
odoo/addons/stock_release_channel_propagate_channel_picking/readme/CONFIGURE.rst
odoo/addons/stock_release_channel_propagate_channel_picking/readme/CONTRIBUTORS.rst
odoo/addons/stock_release_channel_propagate_channel_picking/readme/DESCRIPTION.rst
odoo/addons/stock_release_channel_propagate_channel_picking/readme/USAGE.rst
odoo/addons/stock_release_channel_propagate_channel_picking/static/description/icon.png
odoo/addons/stock_release_channel_propagate_channel_picking/static/description/index.html
odoo/addons/stock_release_channel_propagate_channel_picking/tests/__init__.py
odoo/addons/stock_release_channel_propagate_channel_picking/tests/test_procurement.py
odoo/addons/stock_release_channel_propagate_channel_picking/views/stock_picking_type.xml
odoo_addon_stock_release_channel_propagate_channel_picking-16.0.1.2.0.1.dist-info/METADATA
odoo_addon_stock_release_channel_propagate_channel_picking-16.0.1.2.0.1.dist-info/WHEEL
odoo_addon_stock_release_channel_propagate_channel_picking-16.0.1.2.0.1.dist-info/top_level.txt
odoo_addon_stock_release_channel_propagate_channel_picking-16.0.1.2.0.1.dist-info/RECORD
