Metadata-Version: 2.1
Name: odoo-addon-stock_release_channel_propagate_channel_picking
Version: 16.0.1.2.0.1
Summary: Allows to propagate the channel to every picking that is created from the original one.
Home-page: https://github.com/OCA/wms
Author: ACSONE SA/NV,Odoo Community Association (OCA)
Author-email: support@odoo-community.org
License: AGPL-3
Classifier: Programming Language :: Python
Classifier: Framework :: Odoo
Classifier: Framework :: Odoo :: 16.0
Classifier: License :: OSI Approved :: GNU Affero General Public License v3
Requires-Python: >=3.10
Requires-Dist: odoo-addon-stock-release-channel <16.1dev,>=16.0dev
Requires-Dist: odoo <16.1dev,>=16.0a
